README.md
setup.cfg
setup.py
boost_collections/__init__.py
boost_collections/zskiplist/__init__.py
boost_collections/zskiplist/constant.py
boost_collections/zskiplist/exception.py
boost_collections/zskiplist/t_zset.c
boost_collections/zskiplist/util.py
boost_collections/zskiplist/zset.py
boost_collections/zskiplist/zset_node.py
boost_collections/zskiplist/zset_obj.py
boost_collections/zskiplist/zskiplist.py
boost_collections/zskiplist/zskiplist_ex.py
boost_collections/zskiplist/zskiplist_level.py
boost_collections/zskiplist/zskiplist_node.py
ratel.egg-info/PKG-INFO
ratel.egg-info/SOURCES.txt
ratel.egg-info/dependency_links.txt
ratel.egg-info/requires.txt
ratel.egg-info/top_level.txt