Metadata-Version: 2.1
Name: ratel
Version: 1.0.1
Summary: Sorted data structure implementation by using skiplist and dict with Python and C
Home-page: https://github.com/524243642/ratel
Author: Bin Zhang
Author-email: 524243642@qq.com
License: MIT
Keywords: ratel
Platform: UNKNOWN
Classifier: Development Status :: 5 - Production/Stable
Classifier: Intended Audience :: Developers
Classifier: License :: OSI Approved :: MIT License
Classifier: Programming Language :: Python :: 2.7
Classifier: Programming Language :: Python :: 3.5
Classifier: Programming Language :: Python :: 3.6
Classifier: Programming Language :: Python :: 3.7
Classifier: Programming Language :: Python :: 3.8
Classifier: Programming Language :: Python :: 3.9
